truepiglatin/__init__.py
TruePigLatin-0.0.2.dist-info/LICENSE
TruePigLatin-0.0.2.dist-info/METADATA
TruePigLatin-0.0.2.dist-info/WHEEL
TruePigLatin-0.0.2.dist-info/top_level.txt
TruePigLatin-0.0.2.dist-info/RECORD
