Metadata-Version: 2.1
Name: TruePigLatin
Version: 0.0.2
Summary: TruePigLatin ——可能是史上运行速度最快、最准（doge）的Pig Latin翻译器
Home-page: https://github.com/CHUA-X/TruePigLatin
Author: CHUA某人
Author-email: CHUA某人 <chua-x@outlook.com>
Project-URL: Homepage, https://github.com/CHUA-X/TruePigLatin
Project-URL: Bug Tracker, https://github.com/CHUA-X/TruePigLatin/issues
Classifier: Development Status :: 3 - Alpha
Classifier: Programming Language :: Python
Classifier: Programming Language :: Python :: 3
Classifier: Programming Language :: Python :: 3 :: Only
Classifier: License :: OSI Approved :: MIT License
Classifier: Natural Language :: Chinese (Simplified)
Classifier: Natural Language :: English
Classifier: Operating System :: Unix
Classifier: Operating System :: POSIX :: Linux
Classifier: Operating System :: MacOS :: MacOS X
Classifier: Operating System :: Microsoft :: Windows
Requires-Python: >=3.6
License-File: LICENSE
